mbu_dev_shared_components/database/__init__.py
mbu_dev_shared_components/database/connection.py
mbu_dev_shared_components/database/constants.py
mbu_dev_shared_components/database/logging.py
mbu_dev_shared_components/database/utility.py
mbu_dev_shared_components/getorganized/__init__.py
mbu_dev_shared_components/getorganized/auth.py
mbu_dev_shared_components/getorganized/cases.py
mbu_dev_shared_components/getorganized/contacts.py
mbu_dev_shared_components/getorganized/documents.py
mbu_dev_shared_components/getorganized/objects.py
mbu_dev_shared_components/google/__init__.py
mbu_dev_shared_components/google/api/__init__.py
mbu_dev_shared_components/google/api/auth.py
mbu_dev_shared_components/google/workspace/__init__.py
mbu_dev_shared_components/google/workspace/alerts.py
mbu_dev_shared_components/msoffice365/__init__.py
mbu_dev_shared_components/msoffice365/excel/__init__.py
mbu_dev_shared_components/msoffice365/excel/excel_reader.py
mbu_dev_shared_components/msoffice365/sharepoint_api/__init__.py
mbu_dev_shared_components/msoffice365/sharepoint_api/files.py
mbu_dev_shared_components/os2forms/__init__.py
mbu_dev_shared_components/os2forms/documents.py
mbu_dev_shared_components/os2forms/forms.py
mbu_dev_shared_components/romexis/__init__.py
mbu_dev_shared_components/romexis/db_handler.py
mbu_dev_shared_components/romexis/helper_functions.py
mbu_dev_shared_components/sap/__init__.py
mbu_dev_shared_components/sap/create_invoice.py
mbu_dev_shared_components/solteqtand/__init__.py
mbu_dev_shared_components/solteqtand/application/__init__.py
mbu_dev_shared_components/solteqtand/application/aftalebog.py
mbu_dev_shared_components/solteqtand/application/app_handler.py
mbu_dev_shared_components/solteqtand/application/appointment.py
mbu_dev_shared_components/solteqtand/application/base_ui.py
mbu_dev_shared_components/solteqtand/application/clinic.py
mbu_dev_shared_components/solteqtand/application/document.py
mbu_dev_shared_components/solteqtand/application/edi_portal.py
mbu_dev_shared_components-4.3.1.dist-info/licenses/LICENSE
mbu_dev_shared_components-4.3.1.dist-info/METADATA
mbu_dev_shared_components-4.3.1.dist-info/WHEEL
mbu_dev_shared_components-4.3.1.dist-info/top_level.txt
mbu_dev_shared_components-4.3.1.dist-info/RECORD
