Metadata-Version: 2.4
Name: mbu_dev_shared_components
Version: 4.3.1
Summary: Shared components to use in RPA projects
Author-email: MBU <rpa@mbu.aarhus.dk>
License-Expression: MIT
Classifier: Programming Language :: Python :: 3
Classifier: Operating System :: Microsoft :: Windows
Requires-Python: >=3.7
License-File: LICENSE
Requires-Dist: cryptography>=43.0.0
Requires-Dist: pyodbc>=5.1.0
Requires-Dist: python-dateutil==2.9.*
Requires-Dist: dotenv
Provides-Extra: getorganized
Requires-Dist: requests_ntlm>=1.2.0; extra == "getorganized"
Provides-Extra: google
Requires-Dist: requests; extra == "google"
Provides-Extra: msoffice
Requires-Dist: openpyxl>=3.1.2; extra == "msoffice"
Requires-Dist: pandas>=2.2.3; extra == "msoffice"
Requires-Dist: office365-rest-python-client; extra == "msoffice"
Provides-Extra: os2forms
Requires-Dist: requests; extra == "os2forms"
Provides-Extra: romexis
Requires-Dist: pyodbc>=5.1.0; extra == "romexis"
Requires-Dist: pillow; extra == "romexis"
Requires-Dist: rawpy; extra == "romexis"
Requires-Dist: numpy; extra == "romexis"
Provides-Extra: sap
Provides-Extra: solteqtand
Requires-Dist: uiautomation; extra == "solteqtand"
Requires-Dist: pyodbc>=5.1.0; extra == "solteqtand"
Requires-Dist: psutil; extra == "solteqtand"
Requires-Dist: docx2pdf; extra == "solteqtand"
Provides-Extra: utils
Requires-Dist: python-dateutil==2.9.*; extra == "utils"
Requires-Dist: cryptography>=43.0.0; extra == "utils"
Provides-Extra: dev
Requires-Dist: pylint; extra == "dev"
Requires-Dist: flake8; extra == "dev"
Requires-Dist: pytest-json-report; extra == "dev"
Requires-Dist: pytest>=7.0; extra == "dev"
Requires-Dist: pytest-dependency>=0.5.1; extra == "dev"
Dynamic: license-file
